[{"FirstName":"smita","LastName":"kadam","Gender":"Female","Email":"smitakadam@gmail.com","Password":"21312312","PhoneNumber":"984612349","Duration":"Monthly"},{"FirstName":"maithili","LastName":"ghodake","Gender":"Female","Email":"maithi@gmail.com","Password":"124","PhoneNumber":"7878787878","Duration":"Yearly"},{"FirstName":"eklavya","LastName":"ghodake","Gender":"Male","Email":"ekalv@gmail.com","Password":"2112412","PhoneNumber":"894968465","Duration":"Quarterly"},{"FirstName":"Shaha","LastName":"Singh","Gender":"Female","Email":"sSingh@gmail.com","Password":"123131","PhoneNumber":"89898898","Duration":"Yearly"},{"FirstName":"shahank","LastName":"singh","Gender":"Male","Email":"s@gmail.com","Password":"12345","PhoneNumber":"9898989898","Duration":"Quarterly"}]